music_engine/__init__.py
music_engine/arrangement.py
music_engine/dsp.py
music_engine/synthesis.py
music_engine/theory.py
music_engine/wave_writer.py
py_synth_engine-0.1.0.dist-info/METADATA
py_synth_engine-0.1.0.dist-info/WHEEL
py_synth_engine-0.1.0.dist-info/top_level.txt
py_synth_engine-0.1.0.dist-info/RECORD
