Metadata-Version: 2.4
Name: py-synth-engine
Version: 0.1.0
Summary: A Python library for algorithmic music generation and audio DSP.
Author-email: Amritansh <amritansh20043@gmail.com>
Project-URL: Homepage, https://github.com/nandy2uy/music-generator
Classifier: Programming Language :: Python :: 3
Classifier: License :: OSI Approved :: MIT License
Classifier: Operating System :: OS Independent
Classifier: Topic :: Multimedia :: Sound/Audio
Requires-Python: >=3.8
Requires-Dist: numpy
Requires-Dist: scipy
Requires-Dist: pydub
